homework/2_triggers/sr_latch.v
`timescale 1ns/10ps

module sr_latch(
	input wire r_i,
	input wire s_i,
	output wire q_o,
	output wire nq_o
);

assign q_o = ~(nq_o | r_i);
assign nq_o = ~(q_o | s_i);

endmodule

homework/2_triggers/d_latch.v
`timescale 1ns/10ps

module d_latch(
	input wire d_i,
	input wire e_i,
	output wire q_o,
	output wire nq_o
);

sr_latch sr(
	.r_i((~d_i)&e_i),
	.s_i(d_i&e_i),
	.q_o(q_o),
	.nq_o(nq_o)
);

endmodule

homework/2_triggers/dff.v
`timescale 1ns/10ps

module dff(
	input wire d_i,
	input wire e_i,
	output wire q_o,
	output wire nq_o
);

d_latch d1(
	.d_i(d_i),
	.e_i(~e_i),
	.q_o(),
	.nq_o()
);

d_latch d2(
	.d_i(d1.q_o),
	.e_i(e_i),
	.q_o(q_o),
	.nq_o(nq_o)
);

endmodule

homework/2_triggers/dff_tb.v
`timescale 1ns/10ps

module dff_tb;

realtime period = 10;

reg d;
reg clk;
wire q;
wire nq;

dff dff_inst(
	.d_i(d),
	.e_i(clk),
	.q_o(q),
	.nq_o(nq)
);

// variable initalization
initial begin
	d <= 1'b0;
	clk <= 1'b0;
end

// clk generation
always #(period/2) clk <= ~clk;

// test dff here
initial
    begin
		$dumpvars;
		
		write_dff(1'b1);
		write_dff(1'b0);
		write_dff(1'b1);
		write_dff(1'b0);
		write_dff(1'b1);
		write_dff(1'b0);
		write_dff(1'b1);
		
        $finish ;
	end

// simple task to write d value on negedge of clk
task write_dff(input val);
	begin
		@(negedge clk);
		d = val;
	end
endtask


endmodule

homework/2_triggers/dump.vcd
$date
	Thu Sep 30 00:10:55 2021
$end
$version
	Icarus Verilog
$end
$timescale
	10ps
$end
$scope module dff_tb $end
$var wire 1 ! q $end
$var wire 1 " nq $end
$var reg 1 # clk $end
$var reg 1 $ d $end
$var real 1 % period $end
$scope module dff_inst $end
$var wire 1 $ d_i $end
$var wire 1 # e_i $end
$var wire 1 ! q_o $end
$var wire 1 " nq_o $end
$scope module d1 $end
$var wire 1 $ d_i $end
$var wire 1 & e_i $end
$var wire 1 ' q_o $end
$var wire 1 ( nq_o $end
$scope module sr $end
$var wire 1 ( nq_o $end
$var wire 1 ' q_o $end
$var wire 1 ) r_i $end
$var wire 1 * s_i $end
$upscope $end
$upscope $end
$scope module d2 $end
$var wire 1 ' d_i $end
$var wire 1 # e_i $end
$var wire 1 ! q_o $end
$var wire 1 " nq_o $end
$scope module sr $end
$var wire 1 " nq_o $end
$var wire 1 ! q_o $end
$var wire 1 + r_i $end
$var wire 1 , s_i $end
$upscope $end
$upscope $end
$upscope $end
$scope task write_dff $end
$var reg 1 - val $end
$upscope $end
$upscope $end
$enddefinitions $end
#0
$dumpvars
0-
0,
0+
1*
0)
0(
1'
1&
r10 %
1$
0#
x"
x!
$end
#500
1!
0"
0*
0&
1,
1#
#1000
1(
0'
1)
1&
0,
1-
0$
0#
#1500
1"
0!
0)
0&
1+
1#
#2000
1'
0(
1*
1&
0+
0-
1$
0#
#2500
1!
0"
0*
0&
1,
1#
#3000
1(
0'
1)
1&
0,
1-
0$
0#
#3500
1"
0!
0)
0&
1+
1#
#4000
1'
0(
1*
1&
0+
0-
1$
0#
#4500
1!
0"
0*
0&
1,
1#
#5000
1(
0'
1)
1&
0,
1-
0$
0#
#5500
1"
0!
0)
0&
1+
1#
#6000
1'
0(
1*
1&
0+
1$
0#
